amazon_textract_helper-0.0.35.data/scripts/amazon-textract
textracthelper/__init__.py
textracthelper/_version.py
textracthelper/examples/employmentapp.png
amazon_textract_helper-0.0.35.dist-info/LICENSE
amazon_textract_helper-0.0.35.dist-info/METADATA
amazon_textract_helper-0.0.35.dist-info/WHEEL
amazon_textract_helper-0.0.35.dist-info/top_level.txt
amazon_textract_helper-0.0.35.dist-info/RECORD
