Metadata-Version: 2.1
Name: amazon-textract-helper
Version: 0.0.35
Summary: Amazon Textract Helper tools
Home-page: https://github.com/aws-samples/amazon-textract-textractor/tree/master/helper
Author: Amazon Rekognition Textract Demoes
Author-email: rekognition-textract-demos@amazon.com
License: Apache License Version 2.0
Keywords: amazon-textract-textractor amazon textract textractor helper
Platform: UNKNOWN
Classifier: Development Status :: 4 - Beta
Classifier: Topic :: Utilities
Classifier: License :: OSI Approved :: Apache Software License
Classifier: Programming Language :: Python :: 3.6
Classifier: Programming Language :: Python :: 3.7
Classifier: Programming Language :: Python :: 3.8
Classifier: Programming Language :: Python :: 3.9
Classifier: Programming Language :: Python :: 3.10
Requires-Python: >=3.6
Requires-Dist: boto3
Requires-Dist: botocore
Requires-Dist: amazon-textract-response-parser (>=0.1.40)
Requires-Dist: amazon-textract-caller (>=0.0.27)
Requires-Dist: amazon-textract-overlayer (>=0.0.10)
Requires-Dist: amazon-textract-prettyprinter (>=0.1.0)
Requires-Dist: Pillow
Requires-Dist: pypdf (<4.0,>=3.1)
